pyrundeck/__init__.py
pyrundeck/rundeck.py
pyrundeck-0.10.0.dist-info/LICENSE
pyrundeck-0.10.0.dist-info/METADATA
pyrundeck-0.10.0.dist-info/WHEEL
pyrundeck-0.10.0.dist-info/top_level.txt
pyrundeck-0.10.0.dist-info/RECORD
