Metadata-Version: 2.1
Name: pyrundeck
Version: 0.10.0
Summary: Python REST API client for Rundeck 2.6+
Home-page: https://github.com/pschmitt/pyrundeck
Author: Philipp Schmitt
Author-email: philipp@schmitt.co
License: GPL3
Platform: UNKNOWN
License-File: LICENSE
Requires-Dist: requests
